setup.py
region_unit_recognizer/__init__.py
region_unit_recognizer/region_unit_recognizer.py
region_unit_recognizer/utils.py
region_unit_recognizer.egg-info/PKG-INFO
region_unit_recognizer.egg-info/SOURCES.txt
region_unit_recognizer.egg-info/dependency_links.txt
region_unit_recognizer.egg-info/not-zip-safe
region_unit_recognizer.egg-info/requires.txt
region_unit_recognizer.egg-info/top_level.txt