Metadata-Version: 1.1
Name: region-unit-recognizer
Version: 0.0.1
Summary: Region Unit Recognizer
Home-page: http://github.com/17zuoye/region_unit_recognizer
Author: David Chen
Author-email: mvjome@gmail.com
License: MIT
Platform: any
Classifier: Intended Audience :: Developers
Classifier: Operating System :: OS Independent
Classifier: Programming Language :: Python
Classifier: Topic :: Software Development :: Libraries :: Python Modules
